odoo/addons/exportar_stock_editorial_xls/README.md
odoo/addons/exportar_stock_editorial_xls/__init__.py
odoo/addons/exportar_stock_editorial_xls/__manifest__.py
odoo/addons/exportar_stock_editorial_xls/controllers/__init__.py
odoo/addons/exportar_stock_editorial_xls/controllers/main.py
odoo/addons/exportar_stock_editorial_xls/doc/RELEASE_NOTES.md
odoo/addons/exportar_stock_editorial_xls/models/__init__.py
odoo/addons/exportar_stock_editorial_xls/models/res_partner.py
odoo/addons/exportar_stock_editorial_xls/models/wizard.py
odoo/addons/exportar_stock_editorial_xls/static/description/banner.png
odoo/addons/exportar_stock_editorial_xls/static/description/icon.png
odoo/addons/exportar_stock_editorial_xls/static/description/index.html
odoo/addons/exportar_stock_editorial_xls/static/description/images/advanced_stock.png
odoo/addons/exportar_stock_editorial_xls/static/description/images/banner.png
odoo/addons/exportar_stock_editorial_xls/static/description/images/barcode_scanning.jpeg
odoo/addons/exportar_stock_editorial_xls/static/description/images/checked.png
odoo/addons/exportar_stock_editorial_xls/static/description/images/cybrosys.png
odoo/addons/exportar_stock_editorial_xls/static/description/images/export.jpeg
odoo/addons/exportar_stock_editorial_xls/static/description/images/export.png
odoo/addons/exportar_stock_editorial_xls/static/description/images/export1.png
odoo/addons/exportar_stock_editorial_xls/static/description/images/export2.png
odoo/addons/exportar_stock_editorial_xls/static/description/images/export3.png
odoo/addons/exportar_stock_editorial_xls/static/description/images/inventory_valuation.png
odoo/addons/exportar_stock_editorial_xls/static/description/images/product_barcode.png
odoo/addons/exportar_stock_editorial_xls/static/description/images/stock_ageing.jpeg
odoo/addons/exportar_stock_editorial_xls/static/src/js/action_manager.js
odoo/addons/exportar_stock_editorial_xls/views/action_manager.xml
odoo13_addon_exportar_stock_editorial_xls-13.0.1.0.4.dist-info/METADATA
odoo13_addon_exportar_stock_editorial_xls-13.0.1.0.4.dist-info/WHEEL
odoo13_addon_exportar_stock_editorial_xls-13.0.1.0.4.dist-info/top_level.txt
odoo13_addon_exportar_stock_editorial_xls-13.0.1.0.4.dist-info/RECORD
