Metadata-Version: 2.1
Name: odoo13-addon-exportar_stock_editorial_xls
Version: 13.0.1.0.4
Requires-Python: >=3.5
Requires-Dist: odoo13-addon-gestion_editorial
Requires-Dist: odoo>=13.0a,<13.1dev
Summary: Muestra el stock actual de productos en la editorial.
Home-page: https://framagit.org/devcontrol
License: AGPL-3
Author: Colectivo DEVCONTROL
Classifier: Programming Language :: Python
Classifier: Framework :: Odoo
Classifier: Framework :: Odoo :: 13.0
Classifier: License :: OSI Approved :: GNU Affero General Public License v3
